{"is_source_file": true, "format": "Python", "description": "This is a Python source file that sets up a FastAPI application, manages import paths, and re-exports the main app object for deployment via uvicorn. It is a top-level module serving as the main entry point for the backend API.", "external_files": ["src/api/main.py"], "external_methods": ["app", "uvicorn integration_backend.main_app:app"], "published": ["app"], "classes": [], "methods": [], "calls": ["os.path.dirname", "os.path.abspath", "os.path.join", "sys.path.insert", "import src.api.main"], "search-terms": ["FastAPI", "main_app", "uvicorn", "src.api.main", "application setup", "top-level module"], "state": 2, "file_id": 57, "knowledge_revision": 458, "git_revision": "fb3b6499ef795fc0caff08b00759ac671c12e6ab", "revision_history": [{"449": ""}, {"458": "fb3b6499ef795fc0caff08b00759ac671c12e6ab"}], "ctags": [{"_type": "tag", "name": "_here", "path": "/home/kavia/workspace/code-generation/jira-confluence-connector-146762-146772/integration_backend/main_app.py", "pattern": "/^_here = os.path.dirname(os.path.abspath(__file__))$/", "language": "Python", "kind": "variable"}, {"_type": "tag", "name": "_src", "path": "/home/kavia/workspace/code-generation/jira-confluence-connector-146762-146772/integration_backend/main_app.py", "pattern": "/^_src = os.path.join(_here, \"src\")$/", "language": "Python", "kind": "variable"}], "hash": "25656e416c3ae69c044d15ca1dbe5045", "format-version": 4, "code-base-name": "integration_backend", "filename": "integration_backend/main_app.py", "fields": [{"name": "_here = os.path.dirname(os.path.abspath(__file__))", "scope": "", "scopeKind": "", "description": "unavailable"}, {"name": "_src = os.path.join(_here, \"src\")", "scope": "", "scopeKind": "", "description": "unavailable"}]}